CHANGES.txt
LICENSE.txt
MANIFEST.in
README.txt
TODO.txt
bootstrap.py
buildout.cfg
setup.py
src/m01/__init__.py
src/m01.fake.egg-info/PKG-INFO
src/m01.fake.egg-info/SOURCES.txt
src/m01.fake.egg-info/dependency_links.txt
src/m01.fake.egg-info/namespace_packages.txt
src/m01.fake.egg-info/not-zip-safe
src/m01.fake.egg-info/requires.txt
src/m01.fake.egg-info/top_level.txt
src/m01/fake/AGGREGATION.txt
src/m01/fake/README.txt
src/m01/fake/__init__.py
src/m01/fake/accumulators.py
src/m01/fake/accumulators.txt
src/m01/fake/aggregation.py
src/m01/fake/aggregation.txt
src/m01/fake/client.py
src/m01/fake/client.txt
src/m01/fake/collection-find.txt
src/m01/fake/collection-update.txt
src/m01/fake/collection.py
src/m01/fake/collection.txt
src/m01/fake/cursor.py
src/m01/fake/database.py
src/m01/fake/database.txt
src/m01/fake/expressions.py
src/m01/fake/expressions.txt
src/m01/fake/finder.py
src/m01/fake/finder.txt
src/m01/fake/helpers.py
src/m01/fake/index.txt
src/m01/fake/testing.py
src/m01/fake/testing.txt
src/m01/fake/tests.py
src/m01/fake/updater.py
src/m01/fake/sandbox/LICENSE-Community.txt