Metadata-Version: 2.1
Name: m01.fake
Version: 3.13.4
Summary: FAke mongodb implementation
Home-page: http://pypi.python.org/pypi/m01.fake
Author: Roger Ineichen, Projekt01 GmbH
Author-email: dev@projekt01.ch
License: ZPL 2.1
Keywords: mongoDB mongo fake
Platform: UNKNOWN
Classifier: Development Status :: 5 - Production/Stable
Classifier: Environment :: Web Environment
Classifier: Framework :: Zope :: 3
Classifier: Intended Audience :: Developers
Classifier: License :: OSI Approved :: Zope Public License
Classifier: Programming Language :: Python
Classifier: Programming Language :: Python :: 2
Classifier: Programming Language :: Python :: 2.7
Classifier: Programming Language :: Python :: 3
Classifier: Programming Language :: Python :: 3.3
Classifier: Natural Language :: English
Classifier: Operating System :: OS Independent
Classifier: Topic :: Database
Provides-Extra: stub
Provides-Extra: test
